tru/__init__.py
tru/cache_exec.py
tru/global_vars.py
tru/io.py
tru/math.py
tru/shell.py
tru/tru.py
tru-0.0.5.dist-info/LICENSE.txt
tru-0.0.5.dist-info/METADATA
tru-0.0.5.dist-info/WHEEL
tru-0.0.5.dist-info/entry_points.txt
tru-0.0.5.dist-info/top_level.txt
tru-0.0.5.dist-info/RECORD
