Metadata-Version: 2.1
Name: tru
Version: 0.0.5
Summary: https://github.com/TroyRetter/TRU
Home-page: UNKNOWN
Author: Troy Retter
Author-email: troyretter@gmail.com
License: UNKNOWN
Platform: UNKNOWN
Classifier: Programming Language :: Python :: 3.5
Requires-Dist: pandas
Requires-Dist: PyYAML
